unified_data/__init__.py
unified_data/api.py
unified_data/utils.py
unified_data/ws_api.py
unified_data/adapters/akshare_adapter.py
unified_data/adapters/base.py
unified_data/adapters/ccxt_adapter.py
unified_data/adapters/yfinance_adapter.py
unified_data/adapters/ccxt_strategies/base.py
unified_data/adapters/ccxt_strategies/binance.py
unified_data/adapters/ccxt_strategies/coinbase.py
unified_data/models/__init__.py
unified_data/models/enums.py
unified_data/models/types.py
unified_data/ws_adapters/__init__.py
unified_data/ws_adapters/base.py
unified_data/ws_adapters/tqsdk_adapter.py
unified_data-0.5.0.dist-info/METADATA
unified_data-0.5.0.dist-info/WHEEL
unified_data-0.5.0.dist-info/top_level.txt
unified_data-0.5.0.dist-info/RECORD
