Metadata-Version: 2.4
Name: unified-data
Version: 0.5.0
Summary: Add your description here
Requires-Python: >=3.12
Requires-Dist: akshare>=1.18.4
Requires-Dist: ccxt>=4.5.30
Requires-Dist: numpy<2
Requires-Dist: polars>=1.36.1
Requires-Dist: pyarrow>=22.0.0
Requires-Dist: tqsdk>=3.8.9
Requires-Dist: yfinance>=1.0
